README.md
setup.py
ethereum2_etl.egg-info/PKG-INFO
ethereum2_etl.egg-info/SOURCES.txt
ethereum2_etl.egg-info/dependency_links.txt
ethereum2_etl.egg-info/entry_points.txt
ethereum2_etl.egg-info/requires.txt
ethereum2_etl.egg-info/top_level.txt
ethereum2etl/__init__.py
ethereum2etl/__main__.py
ethereum2etl/api/__init__.py
ethereum2etl/api/build_api.py
ethereum2etl/api/ethereum2_teku_api.py
ethereum2etl/api/rate_limiting_proxy.py
ethereum2etl/api/request.py
ethereum2etl/cli/__init__.py
ethereum2etl/cli/export_beacon_blocks.py
ethereum2etl/cli/export_beacon_committees.py
ethereum2etl/cli/export_beacon_validators.py
ethereum2etl/cli/get_block_range_for_date.py
ethereum2etl/cli/get_epoch_range_for_date.py
ethereum2etl/domain/__init__.py
ethereum2etl/domain/attestation.py
ethereum2etl/domain/attester_slashing.py
ethereum2etl/domain/beacon_block.py
ethereum2etl/domain/committee.py
ethereum2etl/domain/deposit.py
ethereum2etl/domain/proposer_slashing.py
ethereum2etl/domain/validator.py
ethereum2etl/domain/voluntary_exit.py
ethereum2etl/enums/__init__.py
ethereum2etl/jobs/__init__.py
ethereum2etl/jobs/export_beacon_blocks_job.py
ethereum2etl/jobs/export_beacon_committees_job.py
ethereum2etl/jobs/export_beacon_validators_job.py
ethereum2etl/jobs/exporters/__init__.py
ethereum2etl/jobs/exporters/ethereum2_item_exporter.py
ethereum2etl/jobs/exporters/item_exporter.py
ethereum2etl/mappers/__init__.py
ethereum2etl/mappers/attestation_mapper.py
ethereum2etl/mappers/attester_slashing_mapper.py
ethereum2etl/mappers/beacon_block_mapper.py
ethereum2etl/mappers/committee_mapper.py
ethereum2etl/mappers/deposit_mapper.py
ethereum2etl/mappers/proposer_slashing_mapper.py
ethereum2etl/mappers/validator_mapper.py
ethereum2etl/mappers/voluntary_exit_mapper.py
ethereum2etl/service/__init__.py
ethereum2etl/service/ethereum2_block_range_service.py
ethereum2etl/service/ethereum2_epoch_range_service.py
ethereum2etl/service/ethereum2_service.py
ethereum2etl/utils/__init__.py
ethereum2etl/utils/string_utils.py
ethereum2etl/utils/timestamp_utils.py
tests/ethereum2etl/__init__.py
tests/ethereum2etl/helpers.py
tests/ethereum2etl/service/__init__.py
tests/ethereum2etl/service/test_ethereum2_block_range_service.py
