Metadata-Version: 2.1
Name: ethereum2-etl
Version: 0.0.7
Summary: Tools for exporting Ethereum 2.0 blockchain data to CSV and JSON
Home-page: https://github.com/blockchain-etl/ethereum2-etl
Author: Evgeny Medvedev
Author-email: evge.medvedev@gmail.com
License: UNKNOWN
Project-URL: Bug Reports, https://github.com/blockchain-etl/ethereum2-etl/issues
Project-URL: Source, https://github.com/blockchain-etl/ethereum2-etl
Keywords: Ethereum,Ethereum 2.0,ETH 2.0
Platform: UNKNOWN
Classifier: Development Status :: 5 - Production/Stable
Classifier: Intended Audience :: Developers
Classifier: License :: OSI Approved :: MIT License
Classifier: Programming Language :: Python :: 3
Classifier: Programming Language :: Python :: 3.6
Classifier: Programming Language :: Python :: 3.7
Classifier: Programming Language :: Python :: 3.8
Requires-Python: >=3.6.0,<4
Provides-Extra: dev
